{"author":[],"genre":{"gro\u00dfraum-ulm-und-raum-heidelberg":["architekten--werkplaner-mwd"],"berlin":["projektmanager-contract-manufacturing-mwd","qualified-person-mwd","head-of-quality-assurance-mwd"],"oberbayern":["projektleiter-bau-pharma-mwd","lead-buyer-bauleistungen-betriebs---anlagentechnik-mwd","head-of-capex-procurement-construction-services-facility-and-manufacturing-equipment-mwd","leiter-digital-marketing-mwd"],"n\u00fcrnberg":["pta-pharmazeutin-oder-pharmareferentin-als-storemanagerin-health-beauty--wellness-mwd","storemitarbeiterin-mwd","manager-regulatory-affairs-mwd"],"gro\u00dfraum-ulm":["manager-produkttransfer-mwd","steuerfachangestelltersteuerfachwirt-mwd-"],"rheinland":["head-of-operations-pharma-mwd","head-of-research--development-pharma-mwd","head-quality-management-mwd","head-global-sales--marketing-mwd"],"region-m\u00fcnchen":["crm-manager-mwd"],"nordrhein-westfalen":["marketing-assistent-mwd","product-manager-mwd"],"schweiz":["senior-expert-validation-mwd"]},"category":{"bau":["architekten--werkplaner-mwd"],"architektur":["architekten--werkplaner-mwd"],"pharma":["projektmanager-contract-manufacturing-mwd","projektleiter-bau-pharma-mwd","lead-buyer-bauleistungen-betriebs---anlagentechnik-mwd","pta-pharmazeutin-oder-pharmareferentin-als-storemanagerin-health-beauty--wellness-mwd","qualified-person-mwd","head-of-quality-assurance-mwd","storemitarbeiterin-mwd","manager-produkttransfer-mwd","head-of-capex-procurement-construction-services-facility-and-manufacturing-equipment-mwd","head-of-operations-pharma-mwd","head-of-research--development-pharma-mwd","crm-manager-mwd","head-quality-management-mwd","head-global-sales--marketing-mwd","senior-expert-validation-mwd","manager-regulatory-affairs-mwd"],"nahrungserg\u00e4nzungsmittel":["projektmanager-contract-manufacturing-mwd","head-of-quality-assurance-mwd","senior-expert-validation-mwd"],"biotechnologie":["projektleiter-bau-pharma-mwd","manager-produkttransfer-mwd","crm-manager-mwd"],"kosmetik":["pta-pharmazeutin-oder-pharmareferentin-als-storemanagerin-health-beauty--wellness-mwd","storemitarbeiterin-mwd","manager-regulatory-affairs-mwd"],"wellness":["pta-pharmazeutin-oder-pharmareferentin-als-storemanagerin-health-beauty--wellness-mwd","storemitarbeiterin-mwd"],"steuerberater":["steuerfachangestelltersteuerfachwirt-mwd-"],"lohnbuchhaltung":["steuerfachangestelltersteuerfachwirt-mwd-"],"finanzbereich":["steuerfachangestelltersteuerfachwirt-mwd-"],"medizintechnik":["head-of-operations-pharma-mwd","head-of-research--development-pharma-mwd","crm-manager-mwd","head-quality-management-mwd","head-global-sales--marketing-mwd"],"online-marketing":["leiter-digital-marketing-mwd","crm-manager-mwd"],"einzelhandel--und-telekommunikationsbranche":["leiter-digital-marketing-mwd"],"fmcg":["leiter-digital-marketing-mwd"],"gesundheitswesen":["leiter-digital-marketing-mwd","marketing-assistent-mwd","product-manager-mwd"],"medieninformatik":["leiter-digital-marketing-mwd"],"marketingagentur":["leiter-digital-marketing-mwd"],"marketing-agentur":["leiter-digital-marketing-mwd"],"naturheilkunde":["leiter-digital-marketing-mwd","manager-regulatory-affairs-mwd"],"medien--und-kommunikationswissenschaften":["leiter-digital-marketing-mwd"],"arzneimittel":["crm-manager-mwd","senior-expert-validation-mwd"],"b2b":["crm-manager-mwd"],"medizinprodukte":["marketing-assistent-mwd","product-manager-mwd"],"pflege":["marketing-assistent-mwd","product-manager-mwd"],"wellness-beauty":["marketing-assistent-mwd","product-manager-mwd"],"medizinische-hautpflege":["marketing-assistent-mwd","product-manager-mwd"],"pharmazeutische-lohnhersteller":["senior-expert-validation-mwd"]},"history":{"2021":{"01":["architekten--werkplaner-mwd"],"05":["projektmanager-contract-manufacturing-mwd","qualified-person-mwd","head-of-quality-assurance-mwd","storemitarbeiterin-mwd","manager-produkttransfer-mwd"],"02":["pta-pharmazeutin-oder-pharmareferentin-als-storemanagerin-health-beauty--wellness-mwd"],"06":["head-of-capex-procurement-construction-services-facility-and-manufacturing-equipment-mwd","steuerfachangestelltersteuerfachwirt-mwd-","head-of-operations-pharma-mwd","head-of-research--development-pharma-mwd"]},"2020":{"09":["projektleiter-bau-pharma-mwd"],"10":["lead-buyer-bauleistungen-betriebs---anlagentechnik-mwd"]},"2022":{"02":["leiter-digital-marketing-mwd"],"03":["crm-manager-mwd","head-quality-management-mwd"],"06":["head-global-sales--marketing-mwd","marketing-assistent-mwd"],"07":["product-manager-mwd"],"09":["senior-expert-validation-mwd"],"11":["manager-regulatory-affairs-mwd"]}},"post":{"architekten--werkplaner-mwd":{"categories":["Bau","Architektur"],"labels":[],"tags":["Architekt","Werkplaner","Architektur","HOAI","VOB","Industriebau","Geschosswohnungsbau","Bauingenieur","Umbau","Renovierung Neubau"],"gallery":[],"image":null,"genre":"Gro\u00dfraum Ulm und Raum Heidelberg","media":"","archived":false,"draft":false,"featured":true,"author":"","title":"Architekten & Werkplaner (m\/w\/d)","permalink":"architekten--werkplaner-mwd","timestamp":1611097200,"summary":"<p><strong>Kreative Macher gesucht<\/strong><\/p>","words":273},"projektmanager-contract-manufacturing-mwd":{"categories":["Pharma","Nahrungserg\u00e4nzungsmittel"],"labels":[],"tags":["Projektmanager","Lohnunternehmen","Change Prozess","Produktion","Pharma","Nahrungserg\u00e4nzung","Vertrieb","Sales","Akquisition","Angebotserstellung","Vertragsverhandlungen","Kunden","Vertrieb","Projektsteuerung","Quality","Regulatory","Production","Fachmessen","CDMO","Contract","Development","Manufacturing"],"gallery":[],"image":null,"genre":"Berlin","media":"","archived":false,"draft":true,"featured":true,"author":"","title":"Business Development Manager Contract Manufacturing (m\/w\/d)","permalink":"projektmanager-contract-manufacturing-mwd","timestamp":1620380926,"summary":"<p><strong>Business-Vorantreiber &amp; Marktexperte<\/strong><\/p>","words":284},"projektleiter-bau-pharma-mwd":{"categories":["Pharma","Biotechnologie"],"labels":[],"tags":["Pharma","Biotechnologie","Projektleiter Bau","Oberbayern","HOAI","Neubau","Umbau","Bauingenieur","Architekt","Maschinenbau","Pharma- oder Wirtschaftsingenieur","Verfahrenstechnik","VOB","GMP"],"gallery":[],"image":null,"genre":"Oberbayern","media":"","archived":false,"draft":true,"featured":true,"author":"","title":"Projektleiter Bau Pharma (m\/w\/d)","permalink":"projektleiter-bau-pharma-mwd","timestamp":1599639855,"summary":"<p><strong>Herausforderung f\u00fcr Organisationstalent<\/strong><\/p>","words":292},"lead-buyer-bauleistungen-betriebs---anlagentechnik-mwd":{"categories":["Pharma"],"labels":[],"tags":["CAPEX","Strategischer Eink\u00e4ufer","VOB","HOAI","GMP","Einkauf von Baudienstleistung","Strategischer Einkauf","Vertragsverhandlungen","Pharmabereich","Category Management","Oberbayern"],"gallery":[],"image":null,"genre":"Oberbayern","media":"","archived":false,"draft":true,"featured":false,"author":"","title":"Lead Buyer Bauleistungen, Betriebs- & Anlagentechnik (m\/w\/d), Category Manager (m\/w\/d) oder Strategischer Eink\u00e4ufer (m\/w\/d)","permalink":"lead-buyer-bauleistungen-betriebs---anlagentechnik-mwd","timestamp":1603969706,"summary":"<p><strong>Mehr bewegen und aktiv gestalten<\/strong><\/p>","words":367},"pta-pharmazeutin-oder-pharmareferentin-als-storemanagerin-health-beauty--wellness-mwd":{"categories":["Pharma","Kosmetik","Wellness"],"labels":[],"tags":["PTA","Pharmazeutin","Drogistin","Kosmetik","Wellness","Arzneimittel","Medizinprodukte","Medizintechnik","Beratung","Heilwissen","Heilpraktiker","Storemanagerin","Health","Beauty","Gesundheit","Sch\u00f6nheit"],"gallery":[],"image":null,"genre":"N\u00fcrnberg","media":"","archived":false,"draft":true,"featured":false,"author":"","title":"PTA, Pharmazeutin oder Pharmareferentin als Storemanagerin Health, Beauty & Wellness (m\/w\/d)","permalink":"pta-pharmazeutin-oder-pharmareferentin-als-storemanagerin-health-beauty--wellness-mwd","timestamp":1613563410,"summary":"<p>&nbsp; &nbsp; &nbsp; &nbsp; &nbsp; &nbsp; &nbsp; \u201eDer Mensch und seine Gesundheit stehen im Mittelpunkt!\u201c<\/p><p>&nbsp; &nbsp; &nbsp; &nbsp; &nbsp; &nbsp; &nbsp; &nbsp; &nbsp; &nbsp; &nbsp; &nbsp; &nbsp; &nbsp; &nbsp; &nbsp; &nbsp; &nbsp; &nbsp; &nbsp; &nbsp; &nbsp; &nbsp; &nbsp; &nbsp; \u201eFachliche und emotionale Beratung f\u00fcr ein ganzheitliches Wohlbefinden.\u201c<\/p><p>\u201eAllt\u00e4gliche Routinen in bedeutungsvolle Momente verwandeln.\u201c<\/p><p>&nbsp; &nbsp; &nbsp; &nbsp; &nbsp; &nbsp; &nbsp; &nbsp; &nbsp; &nbsp; &nbsp; &nbsp; &nbsp; &nbsp; &nbsp; &nbsp; &nbsp; &nbsp; &nbsp; &nbsp; &nbsp; &nbsp; &nbsp; \u201eProdukte im exklusiven Ambiente mit allen Sinnen erleben.\u201c<\/p><p>&nbsp; &nbsp; &nbsp; &nbsp; &nbsp; &nbsp; &nbsp; &nbsp; &nbsp; &nbsp; &nbsp; &nbsp; &nbsp;\u201eInnehalten und den wichtigen Dingen mehr Aufmerksamkeit schenken.\u201c<\/p>","words":254},"qualified-person-mwd":{"categories":["Pharma"],"labels":[],"tags":["Sachkundige Person","\u00a715 AMG","Qualified Person","Herstellung","Pharma","Pr\u00fcfung","Arzneimittel","Change Prozess","GMP","AMG","PQR","APR","Qualit\u00e4t","QMS","Qualit\u00e4tsmanagementsystem","Audit","Zertifizierung","CAPA","Quality","Pharmazie","Pharmacy","Apotheker","Approbation"],"gallery":[],"image":null,"genre":"Berlin","media":"","archived":false,"draft":true,"featured":true,"author":"","title":"QUALIFIED PERSON (m\/w\/d)","permalink":"qualified-person-mwd","timestamp":1620385515,"summary":"<p><strong>Bereit Qualit\u00e4t neu zu definieren?<\/strong><\/p>","words":272},"head-of-quality-assurance-mwd":{"categories":["Pharma","Nahrungserg\u00e4nzungsmittel"],"labels":[],"tags":["Quality Assurance","Pharma","Leiter Qualit\u00e4tssicherheit","AMG","Produktqualit\u00e4t","Prozess","Qualit\u00e4t","Pharmazie","Biologie","Chemie","Audit","GMP","GXP","TQM","Digitalisierung","Qualit\u00e4tsnormen","Lebensmittel","NEM"],"gallery":[],"image":null,"genre":"Berlin","media":"","archived":false,"draft":true,"featured":true,"author":"","title":"HEAD OF QUALITY ASSURANCE (m\/w\/d)","permalink":"head-of-quality-assurance-mwd","timestamp":1620639283,"summary":"<p><strong>Qualit\u00e4t neu definieren!<\/strong><\/p>","words":265},"storemitarbeiterin-mwd":{"categories":["Pharma","Kosmetik","Wellness"],"labels":[],"tags":["PTA","Pharmazeutin","Drogistin","Kosmetik","Wellness","Arzneimittel","Medizinprodukte","Medizintechnik","Beratung","Heilwissen","Heilpraktiker","Health","Beauty","Gesundheit","Sch\u00f6nheit","Verkauf"],"gallery":[],"image":null,"genre":"N\u00fcrnberg","media":"","archived":false,"draft":true,"featured":false,"author":"","title":"Storemitarbeiter*in Health, Beauty & Wellness (m\/w\/d)","permalink":"storemitarbeiterin-mwd","timestamp":1620640571,"summary":"<p>&nbsp; \u201eDer Mensch und seine Gesundheit stehen im Mittelpunkt!\u201c<\/p><p>&nbsp; &nbsp; &nbsp; &nbsp; &nbsp; &nbsp; &nbsp; &nbsp; &nbsp; &nbsp; &nbsp; &nbsp; &nbsp; &nbsp; &nbsp; &nbsp; &nbsp; &nbsp; &nbsp; &nbsp; &nbsp; &nbsp; &nbsp; &nbsp; &nbsp; \u201eFachliche und emotionale Beratung f\u00fcr ein ganzheitliches Wohlbefinden.\u201c<\/p><p>\u201eAllt\u00e4gliche Routinen in bedeutungsvolle Momente verwandeln.\u201c<\/p><p>&nbsp; &nbsp; &nbsp; &nbsp; &nbsp; &nbsp; &nbsp; &nbsp; &nbsp; &nbsp; &nbsp; &nbsp; &nbsp; &nbsp; &nbsp; &nbsp; &nbsp; &nbsp; &nbsp; &nbsp; &nbsp; &nbsp; &nbsp; \u201eProdukte im exklusiven Ambiente mit allen Sinnen erleben.\u201c<\/p><p>&nbsp; &nbsp; &nbsp; &nbsp; &nbsp; &nbsp; &nbsp; &nbsp; &nbsp; &nbsp; &nbsp; &nbsp; &nbsp;\u201eInnehalten und den wichtigen Dingen mehr Aufmerksamkeit schenken.\u201c<\/p>","words":197},"manager-produkttransfer-mwd":{"categories":["Biotechnologie","Pharma"],"labels":[],"tags":["Manager Produkttransfer","Tech Transfer","Biotechnologie","Pharma","GMP","Pharmazie","Arzneimittel","Produktion","Analytik","Validierung","Technologie","Prozesse","Schnittstelle","internationale Kunden","Solida","Liquida","Pharmaunternehmen","Impfstoffe"],"gallery":[],"image":null,"genre":"Gro\u00dfraum Ulm","media":"","archived":false,"draft":true,"featured":true,"author":"","title":"Manager Tech Transfer","permalink":"manager-produkttransfer-mwd","timestamp":1621498640,"summary":"<p><strong>An der Schnittstelle zwischen Entwicklung und Herstellung<\/strong><\/p>","words":187},"head-of-capex-procurement-construction-services-facility-and-manufacturing-equipment-mwd":{"categories":["Pharma"],"labels":[],"tags":["CAPEX","F\u00fchrungsposition","Team Leader","Strategischer Eink\u00e4ufer","VOB","HOAI","GMP","Einkauf von Baudienstleistung","Strategischer Einkauf","Vertragsverhandlungen","Pharmabereich","Category Management","Oberbayern","Anlagentechnik","Nachtragsmanagement"],"gallery":[],"image":null,"genre":"Oberbayern","media":"","archived":false,"draft":true,"featured":true,"author":"","title":"Head of CAPEX Procurement Construction Services, Facility and Manufacturing Equipment (m\/w\/d)","permalink":"head-of-capex-procurement-construction-services-facility-and-manufacturing-equipment-mwd","timestamp":1623395338,"summary":"<p><strong>Leistungsaufgabe im strategischen Pharma-Einkauf<\/strong><\/p>","words":358},"steuerfachangestelltersteuerfachwirt-mwd-":{"categories":["Steuerberater","Lohnbuchhaltung","Finanzbereich"],"labels":[],"tags":["Bilanzen","Steuern","Bilanzbuchhalter","Buchhaltung","Steuerfachangestellte","Steuerfachwirt","Finanzen","Lohnbuchhaltung","Lohnabrechnung"],"gallery":[],"image":null,"genre":"Gro\u00dfraum Ulm","media":"","archived":false,"draft":false,"featured":true,"author":"","title":"Steuerfachangestellter\/Steuerfachwirt (m\/w\/d)  ","permalink":"steuerfachangestelltersteuerfachwirt-mwd-","timestamp":1624960743,"summary":"<p><strong>Beratung statt Routine. Fachlich. Professionell. Zeitgem\u00e4\u00df.<\/strong><\/p><p>&nbsp;<\/p>","words":326},"head-of-operations-pharma-mwd":{"categories":["Pharma","Medizintechnik"],"labels":[],"tags":["Dermatologie","Pharma","Gesch\u00e4ftsleitung","Vorstand","Head of Operations Pharma","F\u00fchrungskraft","Medizintechnik","Medizinprodukte"],"gallery":[],"image":null,"genre":"Rheinland","media":"","archived":false,"draft":true,"featured":false,"author":"","title":"Head of Operations Pharma (m\/w\/d)","permalink":"head-of-operations-pharma-mwd","timestamp":1624964605,"summary":"<p><strong>Perspektive f\u00fcr unternehmerische F\u00fchrungskraft<\/strong><\/p><p><strong>Mitglied der Gesch\u00e4ftsleitung \/ Mitglied des Vorstands<\/strong><\/p>","words":164},"head-of-research--development-pharma-mwd":{"categories":["Pharma","Medizintechnik"],"labels":[],"tags":["Pharma","Dermatologie","Medizintechnik","Medizinprodukte","Gesch\u00e4ftsleitung","Vorstand","F\u00fchrungskraft","Head of Research & Development Pharma"],"gallery":[],"image":null,"genre":"Rheinland","media":"","archived":false,"draft":true,"featured":true,"author":"","title":"Head of Research & Development Pharma (m\/w\/d)","permalink":"head-of-research--development-pharma-mwd","timestamp":1624965019,"summary":"<p><strong>Perspektive f\u00fcr unternehmerische F\u00fchrungskraft<\/strong><\/p><p><strong>Mitglied der Gesch\u00e4ftsleitung \/ Mitglied des Vorstands<\/strong><\/p>","words":157},"leiter-digital-marketing-mwd":{"categories":["Online-Marketing","Einzelhandel- und Telekommunikationsbranche","FMCG","Gesundheitswesen","Medieninformatik","Marketingagentur","Marketing Agentur","Naturheilkunde","Medien- und Kommunikationswissenschaften"],"labels":[],"tags":["Social Media Manager","SEO","SEA","SEM","Community Management","Content Marketing","Kampagnenmanagement","e-Commerce"],"gallery":[],"image":null,"genre":"Oberbayern","media":"","archived":false,"draft":true,"featured":false,"author":"","title":"Leiter Digitales Marketing (m\/w\/d)","permalink":"leiter-digital-marketing-mwd","timestamp":1645607849,"summary":"<p><strong>Elektrosmog und Feinstaubbelastung reduzieren.<\/strong><\/p><p><strong>Gesundheit sch\u00fctzen. Lebensqualit\u00e4t verbessern<\/strong>.<\/p>","words":293},"crm-manager-mwd":{"categories":["Pharma","Biotechnologie","Arzneimittel","Medizintechnik","Online-Marketing","B2B"],"labels":[],"tags":["CRM Manager","IT","Digitalisierung","Projektmanager","Projektleitung","Kundenbeziehungsmanagement","Customer Journey"],"gallery":[],"image":null,"genre":"Region M\u00fcnchen","media":"","archived":false,"draft":true,"featured":true,"author":"","title":"CRM Manager (m\/w\/d)","permalink":"crm-manager-mwd","timestamp":1646993064,"summary":"<p><strong>Kompetent in Strategie &amp; Konzeption? Stark in pragmatischer Umsetzung?<\/strong><\/p><p><br><\/p>","words":274},"head-quality-management-mwd":{"categories":["Pharma","Medizintechnik"],"labels":[],"tags":["Pharma","Dermatologie","Medizintechnik","Medizinprodukte","Head Quality Management","F\u00fchrungskraft","QMS","GXP"],"gallery":[],"image":null,"genre":"Rheinland","media":"","archived":false,"draft":true,"featured":true,"author":"","title":"Head Quality Management (m\/w\/d)","permalink":"head-quality-management-mwd","timestamp":1647957300,"summary":"<p><strong>Vielseitige, verantwortungsvolle Aufgabe&nbsp;<\/strong><br><strong>f\u00fcr strategisch-konzeptionelle und pragmatische F\u00fchrungskraft<\/strong><\/p>","words":335},"head-global-sales--marketing-mwd":{"categories":["Pharma","Medizintechnik"],"labels":[],"tags":["Pharma","Dermatologie","Medizintechnik","Gesch\u00e4ftsleitung","Head of Global Sales & Marketing"],"gallery":[],"image":null,"genre":"Rheinland","media":"","archived":false,"draft":true,"featured":true,"author":"","title":"Head Global Sales & Marketing (m\/w\/d)","permalink":"head-global-sales--marketing-mwd","timestamp":1655125409,"summary":"<p><strong>Perspektive f\u00fcr F\u00fchrungspers\u00f6nlichkeit: Gesch\u00e4ftsf\u00fchrer<\/strong><\/p>","words":269},"marketing-assistent-mwd":{"categories":["Medizinprodukte","Gesundheitswesen","Pflege","Wellness & Beauty","medizinische Hautpflege"],"labels":[],"tags":["Marketing Assistent","Marktentwicklung","Marktforschung"],"gallery":[],"image":null,"genre":" Nordrhein-Westfalen","media":"","archived":false,"draft":true,"featured":true,"author":"","title":"Marketing Assistent (m\/w\/d)","permalink":"marketing-assistent-mwd","timestamp":1655818907,"summary":"<p><strong>Gestaltungsfreiraum f\u00fcr Organisationstalent<\/strong><\/p>","words":305},"product-manager-mwd":{"categories":["Medizinprodukte","Gesundheitswesen","Pflege","Wellness & Beauty","medizinische Hautpflege"],"labels":[],"tags":["product-manager","Produkt Management","Marktforschung","Marketing"],"gallery":[],"image":null,"genre":"Nordrhein-Westfalen","media":"","archived":false,"draft":false,"featured":true,"author":"","title":"Product Manager (m\/w\/d)","permalink":"product-manager-mwd","timestamp":1656939141,"summary":"<p><strong>Erwecke eine Top-Marke zu neuem Leben!<\/strong><\/p>","words":348},"senior-expert-validation-mwd":{"categories":["Pharma","Nahrungserg\u00e4nzungsmittel","pharmazeutische Lohnhersteller","Arzneimittel"],"labels":[],"tags":["Senior Expert Validation","GMP","Projektmanager","Validierung","Tech Transfer"],"gallery":[],"image":null,"genre":"Schweiz","media":"","archived":false,"draft":false,"featured":true,"author":"","title":"Senior Expert Validation (m\/w\/d)","permalink":"senior-expert-validation-mwd","timestamp":1664266111,"summary":"<p><strong>Prozesse im GMP-Umfeld bei unterschiedlichen Lohnherstellern betreuen und aktiv mitgestalten<\/strong><\/p><p><strong>Sie sind in der Validierung versiert, wollen jedoch zus\u00e4tzlich spannende Projekte in der Entwicklung, Produktion und\/oder Logistik managen?<\/strong><\/p>","words":314},"manager-regulatory-affairs-mwd":{"categories":["Pharma","Naturheilkunde","Kosmetik"],"labels":[],"tags":["Pharma","Arzneimittel","Medizinprodukte","Medizintechnik"],"gallery":[],"image":null,"genre":"N\u00fcrnberg","media":"","archived":false,"draft":false,"featured":true,"author":"","title":"Manager Regulatory Affairs (m\/w\/d)","permalink":"manager-regulatory-affairs-mwd","timestamp":1667915286,"summary":"<p><strong>Abwechslungsreiche Aufgabe in der Arzneimittelzulassung bei expandierendem, familienfreundlichem Unternehmen mit gro\u00dfz\u00fcgiger Homeoffice Option<\/strong><\/p><p><br><\/p>","words":280}},"tag":{"architekt":["architekten--werkplaner-mwd","projektleiter-bau-pharma-mwd"],"werkplaner":["architekten--werkplaner-mwd"],"architektur":["architekten--werkplaner-mwd"],"hoai":["architekten--werkplaner-mwd","projektleiter-bau-pharma-mwd","lead-buyer-bauleistungen-betriebs---anlagentechnik-mwd","head-of-capex-procurement-construction-services-facility-and-manufacturing-equipment-mwd"],"vob":["architekten--werkplaner-mwd","projektleiter-bau-pharma-mwd","lead-buyer-bauleistungen-betriebs---anlagentechnik-mwd","head-of-capex-procurement-construction-services-facility-and-manufacturing-equipment-mwd"],"industriebau":["architekten--werkplaner-mwd"],"geschosswohnungsbau":["architekten--werkplaner-mwd"],"bauingenieur":["architekten--werkplaner-mwd","projektleiter-bau-pharma-mwd"],"umbau":["architekten--werkplaner-mwd","projektleiter-bau-pharma-mwd"],"renovierung-neubau":["architekten--werkplaner-mwd"],"projektmanager":["projektmanager-contract-manufacturing-mwd","crm-manager-mwd","senior-expert-validation-mwd"],"lohnunternehmen":["projektmanager-contract-manufacturing-mwd"],"change-prozess":["projektmanager-contract-manufacturing-mwd","qualified-person-mwd"],"produktion":["projektmanager-contract-manufacturing-mwd","manager-produkttransfer-mwd"],"pharma":["projektmanager-contract-manufacturing-mwd","projektleiter-bau-pharma-mwd","qualified-person-mwd","head-of-quality-assurance-mwd","manager-produkttransfer-mwd","head-of-operations-pharma-mwd","head-of-research--development-pharma-mwd","head-quality-management-mwd","head-global-sales--marketing-mwd","manager-regulatory-affairs-mwd"],"nahrungserg\u00e4nzung":["projektmanager-contract-manufacturing-mwd"],"vertrieb":["projektmanager-contract-manufacturing-mwd","projektmanager-contract-manufacturing-mwd"],"sales":["projektmanager-contract-manufacturing-mwd"],"akquisition":["projektmanager-contract-manufacturing-mwd"],"angebotserstellung":["projektmanager-contract-manufacturing-mwd"],"vertragsverhandlungen":["projektmanager-contract-manufacturing-mwd","lead-buyer-bauleistungen-betriebs---anlagentechnik-mwd","head-of-capex-procurement-construction-services-facility-and-manufacturing-equipment-mwd"],"kunden":["projektmanager-contract-manufacturing-mwd"],"projektsteuerung":["projektmanager-contract-manufacturing-mwd"],"quality":["projektmanager-contract-manufacturing-mwd","qualified-person-mwd"],"regulatory":["projektmanager-contract-manufacturing-mwd"],"production":["projektmanager-contract-manufacturing-mwd"],"fachmessen":["projektmanager-contract-manufacturing-mwd"],"cdmo":["projektmanager-contract-manufacturing-mwd"],"contract":["projektmanager-contract-manufacturing-mwd"],"development":["projektmanager-contract-manufacturing-mwd"],"manufacturing":["projektmanager-contract-manufacturing-mwd"],"biotechnologie":["projektleiter-bau-pharma-mwd","manager-produkttransfer-mwd"],"projektleiter-bau":["projektleiter-bau-pharma-mwd"],"oberbayern":["projektleiter-bau-pharma-mwd","lead-buyer-bauleistungen-betriebs---anlagentechnik-mwd","head-of-capex-procurement-construction-services-facility-and-manufacturing-equipment-mwd"],"neubau":["projektleiter-bau-pharma-mwd"],"maschinenbau":["projektleiter-bau-pharma-mwd"],"pharma--oder-wirtschaftsingenieur":["projektleiter-bau-pharma-mwd"],"verfahrenstechnik":["projektleiter-bau-pharma-mwd"],"gmp":["projektleiter-bau-pharma-mwd","lead-buyer-bauleistungen-betriebs---anlagentechnik-mwd","qualified-person-mwd","head-of-quality-assurance-mwd","manager-produkttransfer-mwd","head-of-capex-procurement-construction-services-facility-and-manufacturing-equipment-mwd","senior-expert-validation-mwd"],"capex":["lead-buyer-bauleistungen-betriebs---anlagentechnik-mwd","head-of-capex-procurement-construction-services-facility-and-manufacturing-equipment-mwd"],"strategischer-eink\u00e4ufer":["lead-buyer-bauleistungen-betriebs---anlagentechnik-mwd","head-of-capex-procurement-construction-services-facility-and-manufacturing-equipment-mwd"],"einkauf-von-baudienstleistung":["lead-buyer-bauleistungen-betriebs---anlagentechnik-mwd","head-of-capex-procurement-construction-services-facility-and-manufacturing-equipment-mwd"],"strategischer-einkauf":["lead-buyer-bauleistungen-betriebs---anlagentechnik-mwd","head-of-capex-procurement-construction-services-facility-and-manufacturing-equipment-mwd"],"pharmabereich":["lead-buyer-bauleistungen-betriebs---anlagentechnik-mwd","head-of-capex-procurement-construction-services-facility-and-manufacturing-equipment-mwd"],"category-management":["lead-buyer-bauleistungen-betriebs---anlagentechnik-mwd","head-of-capex-procurement-construction-services-facility-and-manufacturing-equipment-mwd"],"pta":["pta-pharmazeutin-oder-pharmareferentin-als-storemanagerin-health-beauty--wellness-mwd","storemitarbeiterin-mwd"],"pharmazeutin":["pta-pharmazeutin-oder-pharmareferentin-als-storemanagerin-health-beauty--wellness-mwd","storemitarbeiterin-mwd"],"drogistin":["pta-pharmazeutin-oder-pharmareferentin-als-storemanagerin-health-beauty--wellness-mwd","storemitarbeiterin-mwd"],"kosmetik":["pta-pharmazeutin-oder-pharmareferentin-als-storemanagerin-health-beauty--wellness-mwd","storemitarbeiterin-mwd"],"wellness":["pta-pharmazeutin-oder-pharmareferentin-als-storemanagerin-health-beauty--wellness-mwd","storemitarbeiterin-mwd"],"arzneimittel":["pta-pharmazeutin-oder-pharmareferentin-als-storemanagerin-health-beauty--wellness-mwd","qualified-person-mwd","storemitarbeiterin-mwd","manager-produkttransfer-mwd","manager-regulatory-affairs-mwd"],"medizinprodukte":["pta-pharmazeutin-oder-pharmareferentin-als-storemanagerin-health-beauty--wellness-mwd","storemitarbeiterin-mwd","head-of-operations-pharma-mwd","head-of-research--development-pharma-mwd","head-quality-management-mwd","manager-regulatory-affairs-mwd"],"medizintechnik":["pta-pharmazeutin-oder-pharmareferentin-als-storemanagerin-health-beauty--wellness-mwd","storemitarbeiterin-mwd","head-of-operations-pharma-mwd","head-of-research--development-pharma-mwd","head-quality-management-mwd","head-global-sales--marketing-mwd","manager-regulatory-affairs-mwd"],"beratung":["pta-pharmazeutin-oder-pharmareferentin-als-storemanagerin-health-beauty--wellness-mwd","storemitarbeiterin-mwd"],"heilwissen":["pta-pharmazeutin-oder-pharmareferentin-als-storemanagerin-health-beauty--wellness-mwd","storemitarbeiterin-mwd"],"heilpraktiker":["pta-pharmazeutin-oder-pharmareferentin-als-storemanagerin-health-beauty--wellness-mwd","storemitarbeiterin-mwd"],"storemanagerin":["pta-pharmazeutin-oder-pharmareferentin-als-storemanagerin-health-beauty--wellness-mwd"],"health":["pta-pharmazeutin-oder-pharmareferentin-als-storemanagerin-health-beauty--wellness-mwd","storemitarbeiterin-mwd"],"beauty":["pta-pharmazeutin-oder-pharmareferentin-als-storemanagerin-health-beauty--wellness-mwd","storemitarbeiterin-mwd"],"gesundheit":["pta-pharmazeutin-oder-pharmareferentin-als-storemanagerin-health-beauty--wellness-mwd","storemitarbeiterin-mwd"],"sch\u00f6nheit":["pta-pharmazeutin-oder-pharmareferentin-als-storemanagerin-health-beauty--wellness-mwd","storemitarbeiterin-mwd"],"sachkundige-person":["qualified-person-mwd"],"\u00a715-amg":["qualified-person-mwd"],"qualified-person":["qualified-person-mwd"],"herstellung":["qualified-person-mwd"],"pr\u00fcfung":["qualified-person-mwd"],"amg":["qualified-person-mwd","head-of-quality-assurance-mwd"],"pqr":["qualified-person-mwd"],"apr":["qualified-person-mwd"],"qualit\u00e4t":["qualified-person-mwd","head-of-quality-assurance-mwd"],"qms":["qualified-person-mwd","head-quality-management-mwd"],"qualit\u00e4tsmanagementsystem":["qualified-person-mwd"],"audit":["qualified-person-mwd","head-of-quality-assurance-mwd"],"zertifizierung":["qualified-person-mwd"],"capa":["qualified-person-mwd"],"pharmazie":["qualified-person-mwd","head-of-quality-assurance-mwd","manager-produkttransfer-mwd"],"pharmacy":["qualified-person-mwd"],"apotheker":["qualified-person-mwd"],"approbation":["qualified-person-mwd"],"quality-assurance":["head-of-quality-assurance-mwd"],"leiter-qualit\u00e4tssicherheit":["head-of-quality-assurance-mwd"],"produktqualit\u00e4t":["head-of-quality-assurance-mwd"],"prozess":["head-of-quality-assurance-mwd"],"biologie":["head-of-quality-assurance-mwd"],"chemie":["head-of-quality-assurance-mwd"],"gxp":["head-of-quality-assurance-mwd","head-quality-management-mwd"],"tqm":["head-of-quality-assurance-mwd"],"digitalisierung":["head-of-quality-assurance-mwd","crm-manager-mwd"],"qualit\u00e4tsnormen":["head-of-quality-assurance-mwd"],"lebensmittel":["head-of-quality-assurance-mwd"],"nem":["head-of-quality-assurance-mwd"],"verkauf":["storemitarbeiterin-mwd"],"manager-produkttransfer":["manager-produkttransfer-mwd"],"tech-transfer":["manager-produkttransfer-mwd","senior-expert-validation-mwd"],"analytik":["manager-produkttransfer-mwd"],"validierung":["manager-produkttransfer-mwd","senior-expert-validation-mwd"],"technologie":["manager-produkttransfer-mwd"],"prozesse":["manager-produkttransfer-mwd"],"schnittstelle":["manager-produkttransfer-mwd"],"internationale-kunden":["manager-produkttransfer-mwd"],"solida":["manager-produkttransfer-mwd"],"liquida":["manager-produkttransfer-mwd"],"pharmaunternehmen":["manager-produkttransfer-mwd"],"impfstoffe":["manager-produkttransfer-mwd"],"f\u00fchrungsposition":["head-of-capex-procurement-construction-services-facility-and-manufacturing-equipment-mwd"],"team-leader":["head-of-capex-procurement-construction-services-facility-and-manufacturing-equipment-mwd"],"anlagentechnik":["head-of-capex-procurement-construction-services-facility-and-manufacturing-equipment-mwd"],"nachtragsmanagement":["head-of-capex-procurement-construction-services-facility-and-manufacturing-equipment-mwd"],"bilanzen":["steuerfachangestelltersteuerfachwirt-mwd-"],"steuern":["steuerfachangestelltersteuerfachwirt-mwd-"],"bilanzbuchhalter":["steuerfachangestelltersteuerfachwirt-mwd-"],"buchhaltung":["steuerfachangestelltersteuerfachwirt-mwd-"],"steuerfachangestellte":["steuerfachangestelltersteuerfachwirt-mwd-"],"steuerfachwirt":["steuerfachangestelltersteuerfachwirt-mwd-"],"finanzen":["steuerfachangestelltersteuerfachwirt-mwd-"],"lohnbuchhaltung":["steuerfachangestelltersteuerfachwirt-mwd-"],"lohnabrechnung":["steuerfachangestelltersteuerfachwirt-mwd-"],"dermatologie":["head-of-operations-pharma-mwd","head-of-research--development-pharma-mwd","head-quality-management-mwd","head-global-sales--marketing-mwd"],"gesch\u00e4ftsleitung":["head-of-operations-pharma-mwd","head-of-research--development-pharma-mwd","head-global-sales--marketing-mwd"],"vorstand":["head-of-operations-pharma-mwd","head-of-research--development-pharma-mwd"],"head-of-operations-pharma":["head-of-operations-pharma-mwd"],"f\u00fchrungskraft":["head-of-operations-pharma-mwd","head-of-research--development-pharma-mwd","head-quality-management-mwd"],"head-of-research-development-pharma":["head-of-research--development-pharma-mwd"],"social-media-manager":["leiter-digital-marketing-mwd"],"seo":["leiter-digital-marketing-mwd"],"sea":["leiter-digital-marketing-mwd"],"sem":["leiter-digital-marketing-mwd"],"community-management":["leiter-digital-marketing-mwd"],"content-marketing":["leiter-digital-marketing-mwd"],"kampagnenmanagement":["leiter-digital-marketing-mwd"],"e-commerce":["leiter-digital-marketing-mwd"],"crm-manager":["crm-manager-mwd"],"it":["crm-manager-mwd"],"projektleitung":["crm-manager-mwd"],"kundenbeziehungsmanagement":["crm-manager-mwd"],"customer-journey":["crm-manager-mwd"],"head-quality-management":["head-quality-management-mwd"],"head-of-global-sales-marketing":["head-global-sales--marketing-mwd"],"marketing-assistent":["marketing-assistent-mwd"],"marktentwicklung":["marketing-assistent-mwd"],"marktforschung":["marketing-assistent-mwd","product-manager-mwd"],"product-manager":["product-manager-mwd"],"produkt-management":["product-manager-mwd"],"marketing":["product-manager-mwd"],"senior-expert-validation":["senior-expert-validation-mwd"]},"label":[],"draft":["projektmanager-contract-manufacturing-mwd","projektleiter-bau-pharma-mwd","lead-buyer-bauleistungen-betriebs---anlagentechnik-mwd","pta-pharmazeutin-oder-pharmareferentin-als-storemanagerin-health-beauty--wellness-mwd","qualified-person-mwd","head-of-quality-assurance-mwd","storemitarbeiterin-mwd","manager-produkttransfer-mwd","head-of-capex-procurement-construction-services-facility-and-manufacturing-equipment-mwd","head-of-operations-pharma-mwd","head-of-research--development-pharma-mwd","leiter-digital-marketing-mwd","crm-manager-mwd","head-quality-management-mwd","head-global-sales--marketing-mwd","marketing-assistent-mwd"],"archived":[],"featured":["architekten--werkplaner-mwd","projektmanager-contract-manufacturing-mwd","projektleiter-bau-pharma-mwd","qualified-person-mwd","head-of-quality-assurance-mwd","manager-produkttransfer-mwd","head-of-capex-procurement-construction-services-facility-and-manufacturing-equipment-mwd","steuerfachangestelltersteuerfachwirt-mwd-","head-of-research--development-pharma-mwd","crm-manager-mwd","head-quality-management-mwd","head-global-sales--marketing-mwd","marketing-assistent-mwd","product-manager-mwd","senior-expert-validation-mwd","manager-regulatory-affairs-mwd"],"version":"20200806"}